zeusdb_vector_database-0.4.1.dist-info/METADATA
zeusdb_vector_database-0.4.1.dist-info/WHEEL
zeusdb_vector_database-0.4.1.dist-info/licenses/LICENSE
zeusdb_vector_database-0.4.1.dist-info/licenses/NOTICE
zeusdb_vector_database/__init__.py
zeusdb_vector_database/logging_config.py
zeusdb_vector_database/py.typed
zeusdb_vector_database/vector_database.py
zeusdb_vector_database/zeusdb_vector_database.cpython-313-aarch64-linux-gnu.so
zeusdb_vector_database-0.4.1.dist-info/RECORD
