Metadata-Version: 2.4
Name: zeusdb-vector-database
Version: 0.4.1
Classifier: Programming Language :: Rust
Classifier: Programming Language :: Python :: Implementation :: CPython
Requires-Dist: numpy>=2.2.6,<3.0.0
Requires-Dist: maturin>=1.9.3 ; extra == 'dev'
Requires-Dist: pytest>=8.4.0 ; extra == 'dev'
Requires-Dist: psutil>=7.0.0 ; extra == 'dev'
Provides-Extra: dev
License-File: LICENSE
License-File: NOTICE
Summary: Blazing-fast vector DB with real-time similarity search and metadata filtering.
Author-email: ZeusDB <contact@zeusdb.com>
License-Expression: Apache-2.0
Requires-Python: >=3.10
Project-URL: Repository, https://github.com/zeusdb/zeusdb-vector-database
Project-URL: Documentation, https://docs.zeusdb.com/en/latest/vector_database/
Project-URL: Bug Tracker, https://github.com/zeusdb/zeusdb-vector-database/issues
